tests/__init__.py
tests/_compat.py
tests/test_caption_formatter.py
tests/test_cli.py
tests/test_config.py
tests/test_download_files.py
tests/test_exceptions.py
tests/test_files.py
tests/test_management.py
tests/test_upload_files.py
tests/test_utils.py
tests/test_video.py
tests/test_client/__init__.py
tests/test_client/test_progress_bar.py
tests/test_client/test_telegram_download_client.py
tests/test_client/test_telegram_manager_client.py
tests/test_client/test_uploady_client.py
uploady/__init__.py
uploady/_compat.py
uploady/caption_formatter.py
uploady/cli.py
uploady/config.py
uploady/download_files.py
uploady/exceptions.py
uploady/management.py
uploady/upload_files.py
uploady/utils.py
uploady/video.py
uploady/client/__init__.py
uploady/client/progress_bar.py
uploady/client/telegram_download_client.py
uploady/client/telegram_manager_client.py
uploady/client/uploady_client.py
uploady-0.0.3.dist-info/AUTHORS.rst
uploady-0.0.3.dist-info/LICENSE
uploady-0.0.3.dist-info/METADATA
uploady-0.0.3.dist-info/WHEEL
uploady-0.0.3.dist-info/entry_points.txt
uploady-0.0.3.dist-info/top_level.txt
uploady-0.0.3.dist-info/RECORD
