Metadata-Version: 2.1
Name: uploady
Version: 0.0.3
Summary: Upload (and download) files to Telegram up to 4 GiB using your account. 
Home-page: https://github.com/ankit-chaubey/uploady/
Download-URL: https://github.com/ankit-chaubey/uploady/archive/master.zip
Author: Ankit Chaubey
Author-email: m.ankitchaubey@gmail.com
Keywords: uploady,telegram,upload,video
Platform: linux
Classifier: License :: OSI Approved :: MIT License
Classifier: Programming Language :: Python :: 3.11
Classifier: Programming Language :: Python :: 3.8
Classifier: Programming Language :: Python :: 3.7
Classifier: Programming Language :: Python :: 3 :: Only
Classifier: Programming Language :: Python :: 3.10
Classifier: Programming Language :: Python :: 3.12
Classifier: Programming Language :: Python :: 3.9
Classifier: Operating System :: POSIX
Classifier: Operating System :: POSIX :: Linux
Classifier: Natural Language :: English
Classifier: Development Status :: 5 - Production/Stable
Provides: tests
Provides: uploady
License-File: LICENSE
License-File: AUTHORS.rst
Requires-Dist: telethon
Requires-Dist: click>=6.0
Requires-Dist: cryptg
Requires-Dist: hachoir
Requires-Dist: prompt-toolkit
Requires-Dist: pysocks
Requires-Dist: more-itertools
Requires-Dist: scandir; python_version < "3.6"
